odoo/addons/web_widget_open_tab/README.rst
odoo/addons/web_widget_open_tab/__init__.py
odoo/addons/web_widget_open_tab/__manifest__.py
odoo/addons/web_widget_open_tab/demo/res_users_view.xml
odoo/addons/web_widget_open_tab/i18n/ca.po
odoo/addons/web_widget_open_tab/i18n/de.po
odoo/addons/web_widget_open_tab/i18n/es.po
odoo/addons/web_widget_open_tab/i18n/it.po
odoo/addons/web_widget_open_tab/i18n/ja.po
odoo/addons/web_widget_open_tab/i18n/pt_BR.po
odoo/addons/web_widget_open_tab/i18n/web_widget_open_tab.pot
odoo/addons/web_widget_open_tab/models/__init__.py
odoo/addons/web_widget_open_tab/models/ir_model.py
odoo/addons/web_widget_open_tab/models/ir_ui_view.py
odoo/addons/web_widget_open_tab/readme/CONTRIBUTORS.md
odoo/addons/web_widget_open_tab/readme/DESCRIPTION.md
odoo/addons/web_widget_open_tab/readme/ROADMAP.md
odoo/addons/web_widget_open_tab/readme/USAGE.md
odoo/addons/web_widget_open_tab/static/description/icon.png
odoo/addons/web_widget_open_tab/static/description/index.html
odoo/addons/web_widget_open_tab/static/src/js/open_tab_widget.esm.js
odoo/addons/web_widget_open_tab/static/src/xml/open_tab_widget.xml
odoo/addons/web_widget_open_tab/tests/__init__.py
odoo/addons/web_widget_open_tab/tests/test_main.py
odoo/addons/web_widget_open_tab/views/ir_model_views.xml
odoo_addon_web_widget_open_tab-18.0.1.0.0.2.dist-info/METADATA
odoo_addon_web_widget_open_tab-18.0.1.0.0.2.dist-info/WHEEL
odoo_addon_web_widget_open_tab-18.0.1.0.0.2.dist-info/top_level.txt
odoo_addon_web_widget_open_tab-18.0.1.0.0.2.dist-info/RECORD
